[
  {
    "date": "2026-07-18",
    "cp": "update",
    "up": 20,
    "down": 45,
    "flat": 35,
    "bias": "down",
    "conv": 40,
    "ifm": 35,
    "notes": "Sin checkpoint 'pre' de referencia hoy (sábado, mercados cerrados); sesgo bajista de continuación tras el rout de semis del viernes y la escalada EEUU-Irán.",
    "result": null
  },
  {
    "date": "2026-07-18",
    "cp": "pre",
    "up": 20,
    "down": 45,
    "flat": 35,
    "bias": "down",
    "conv": 55,
    "ifm": 38,
    "notes": "Sesgo bajista: rout de semis (SOX -9% semanal) tras Kimi K3 de Moonshot y escalada EEUU-Irán en Ormuz (WTI +14% semanal); sin dato overnight real por cierre de fin de semana.",
    "result": null
  },
  {
    "date": "2026-07-19",
    "cp": "update",
    "up": 18,
    "down": 50,
    "flat": 32,
    "bias": "down",
    "conv": 45,
    "ifm": 30,
    "notes": "Sin checkpoint 'pre' de hoy (mercados cerrados, futuros aún sin reabrir); sesgo bajista reforzado tras 2 militares de EEUU muertos en Jordania y ruptura del memorando Irán-EEUU, sin confirmación de precio aún.",
    "result": null
  },
  {
    "date": "2026-07-19",
    "cp": "pre",
    "up": 12,
    "down": 60,
    "flat": 28,
    "bias": "down",
    "conv": 65,
    "ifm": 20,
    "notes": "Fuertemente bajista: guerra activa EEUU-Irán (8ª noche), 2 militares de EEUU muertos y 1 desaparecido en ataque a base de Jordania, MOU suspendido por Irán, más rout de semis (SOX/SMH -6% semanal); sin dato overnight real de NQ por cierre de fin de semana.",
    "result": null
  },
  {
    "date": "2026-07-19",
    "cp": "update",
    "up": 12,
    "down": 60,
    "flat": 28,
    "bias": "down",
    "conv": 65,
    "ifm": 20,
    "notes": "Sin cambios materiales confirmados desde el informe de 14:45; futuros CME siguen cerrados (reabren ~00:00 CEST) y no hay overnight de NQ. Escalada EEUU-Irán y rout de semis se mantienen como tesis vigente sin nuevos catalizadores verificados.",
    "result": null
  },
  {
    "date": "2026-07-20",
    "cp": "update",
    "up": 45,
    "down": 30,
    "flat": 25,
    "bias": "up",
    "conv": 40,
    "ifm": 45,
    "notes": "Sin checkpoint 'pre' de hoy disponible; con mercado ya abierto el precio contradice la tesis bajista del fin de semana: S&P500 +0.5% y Nasdaq +0.8% liderados por el rebote de semis, pese a que la guerra EEUU-Irán se agrava (17 militares muertos) y el VIX sube frente al viernes.",
    "result": null
  },
  {
    "date": "2026-07-20",
    "cp": "pre",
    "up": 55,
    "down": 20,
    "flat": 25,
    "bias": "up",
    "conv": 60,
    "ifm": 62,
    "notes": "Rebote alcista tras el rout de semis: futuros NQ +0.76% premarket y Nasdaq Composite +1% intradia, VIX cede a 18.2, pese a 9a noche de escalada EEUU-Iran y SOXX en mercado bajista tecnico (-20% desde el pico de junio).",
    "result": null
  }
]
